odoo/addons/rma_sale/README.rst
odoo/addons/rma_sale/__init__.py
odoo/addons/rma_sale/__manifest__.py
odoo/addons/rma_sale/controllers/__init__.py
odoo/addons/rma_sale/controllers/rma_portal.py
odoo/addons/rma_sale/controllers/sale_portal.py
odoo/addons/rma_sale/i18n/de.po
odoo/addons/rma_sale/i18n/es.po
odoo/addons/rma_sale/i18n/fr.po
odoo/addons/rma_sale/i18n/it.po
odoo/addons/rma_sale/i18n/nl.po
odoo/addons/rma_sale/i18n/pt.po
odoo/addons/rma_sale/i18n/pt_BR.po
odoo/addons/rma_sale/i18n/rma_sale.pot
odoo/addons/rma_sale/i18n/ro.po
odoo/addons/rma_sale/models/__init__.py
odoo/addons/rma_sale/models/account_move.py
odoo/addons/rma_sale/models/res_company.py
odoo/addons/rma_sale/models/res_config_settings.py
odoo/addons/rma_sale/models/rma.py
odoo/addons/rma_sale/models/sale.py
odoo/addons/rma_sale/readme/CONTRIBUTORS.md
odoo/addons/rma_sale/readme/DESCRIPTION.md
odoo/addons/rma_sale/readme/ROADMAP.md
odoo/addons/rma_sale/readme/USAGE.md
odoo/addons/rma_sale/security/ir.model.access.csv
odoo/addons/rma_sale/static/description/icon.png
odoo/addons/rma_sale/static/description/index.html
odoo/addons/rma_sale/static/src/js/rma_portal_form.esm.js
odoo/addons/rma_sale/static/src/scss/rma_sale.scss
odoo/addons/rma_sale/static/src/tests/test_rma_sale_portal_tour.esm.js
odoo/addons/rma_sale/tests/__init__.py
odoo/addons/rma_sale/tests/test_rma_sale.py
odoo/addons/rma_sale/tests/test_rma_sale_allowed_qty.py
odoo/addons/rma_sale/tests/test_rma_sale_portal.py
odoo/addons/rma_sale/views/account_move_views.xml
odoo/addons/rma_sale/views/report_rma.xml
odoo/addons/rma_sale/views/res_config_settings_views.xml
odoo/addons/rma_sale/views/rma_views.xml
odoo/addons/rma_sale/views/sale_portal_template.xml
odoo/addons/rma_sale/views/sale_views.xml
odoo/addons/rma_sale/wizard/__init__.py
odoo/addons/rma_sale/wizard/sale_order_rma_wizard.py
odoo/addons/rma_sale/wizard/sale_order_rma_wizard_views.xml
odoo/addons/rma_sale/wizard/stock_picking_return.py
odoo_addon_rma_sale-18.0.2.0.2.dist-info/METADATA
odoo_addon_rma_sale-18.0.2.0.2.dist-info/WHEEL
odoo_addon_rma_sale-18.0.2.0.2.dist-info/top_level.txt
odoo_addon_rma_sale-18.0.2.0.2.dist-info/RECORD
